brainscale/__init__.py
brainscale/_compatible_imports.py
brainscale/_compatible_imports_test.py
brainscale/_etrace_algorithms.py
brainscale/_etrace_compiler_base.py
brainscale/_etrace_compiler_graph.py
brainscale/_etrace_compiler_graph_test.py
brainscale/_etrace_compiler_hid_param_op.py
brainscale/_etrace_compiler_hid_param_op_test.py
brainscale/_etrace_compiler_hidden_group.py
brainscale/_etrace_compiler_hidden_group_test.py
brainscale/_etrace_compiler_hidden_pertubation.py
brainscale/_etrace_compiler_hidden_pertubation_test.py
brainscale/_etrace_compiler_module_info.py
brainscale/_etrace_compiler_module_info_test.py
brainscale/_etrace_concepts.py
brainscale/_etrace_concepts_test.py
brainscale/_etrace_debug_jaxpr2code.py
brainscale/_etrace_debug_visualize.py
brainscale/_etrace_graph_executor.py
brainscale/_etrace_graph_executor_test.py
brainscale/_etrace_input_data.py
brainscale/_etrace_input_data_test.py
brainscale/_etrace_model_test.py
brainscale/_etrace_model_with_group_state.py
brainscale/_etrace_operators.py
brainscale/_etrace_operators_test.py
brainscale/_etrace_vjp_algorithms.py
brainscale/_etrace_vjp_algorithms_test.py
brainscale/_etrace_vjp_graph_executor.py
brainscale/_etrace_vjp_graph_executor_test.py
brainscale/_grad_exponential.py
brainscale/_misc.py
brainscale/_state_managment.py
brainscale/_typing.py
brainscale/nn/__init__.py
brainscale/nn/_conv.py
brainscale/nn/_conv_test.py
brainscale/nn/_linear.py
brainscale/nn/_linear_test.py
brainscale/nn/_normalizations.py
brainscale/nn/_normalizations_test.py
brainscale/nn/_readout.py
brainscale/nn/_readout_test.py
brainscale/nn/_rnn.py
brainscale/nn/_rnn_test.py
brainscale-0.1.0.dist-info/licenses/LICENSE
brainscale-0.1.0.dist-info/METADATA
brainscale-0.1.0.dist-info/WHEEL
brainscale-0.1.0.dist-info/top_level.txt
brainscale-0.1.0.dist-info/RECORD
