Metadata-Version: 2.4
Name: brainscale
Version: 0.1.0
Summary: Enabling Scalable Online Learning for Brain Dynamics.
Author-email: BrainScale Developers <chao.brain@qq.com>
License: Apache-2.0 license
Project-URL: Homepage, https://github.com/chaobrain/brainscale
Project-URL: Bug Tracker, https://github.com/chaobrain/brainscale/issues
Project-URL: Documentation, https://brainscale.readthedocs.io/
Project-URL: Source Code, https://github.com/chaobrain/brainscale
Keywords: computational neuroscience,brain-inspired computing,brain modeling,online learning
Classifier: Natural Language :: English
Classifier: Operating System :: OS Independent
Classifier: Programming Language :: Python
Classifier: Programming Language :: Python :: 3
Classifier: Programming Language :: Python :: 3.10
Classifier: Programming Language :: Python :: 3.11
Classifier: Programming Language :: Python :: 3.12
Classifier: Programming Language :: Python :: 3.13
Classifier: Intended Audience :: Science/Research
Classifier: License :: OSI Approved :: Apache Software License
Classifier: Topic :: Scientific/Engineering :: Bio-Informatics
Classifier: Topic :: Scientific/Engineering :: Mathematics
Classifier: Topic :: Scientific/Engineering :: Artificial Intelligence
Classifier: Topic :: Software Development :: Libraries
Requires-Python: >=3.10
License-File: LICENSE
Requires-Dist: brainstate>=0.2.2
Requires-Dist: brainunit
Requires-Dist: brainstate
Requires-Dist: brainpy>=2.7.1
Requires-Dist: braintools
Provides-Extra: cpu
Requires-Dist: jax[cpu]; extra == "cpu"
Requires-Dist: brainunit; extra == "cpu"
Requires-Dist: brainstate; extra == "cpu"
Requires-Dist: brainpy; extra == "cpu"
Requires-Dist: braintools; extra == "cpu"
Provides-Extra: cuda12
Requires-Dist: jax[cuda12]; extra == "cuda12"
Requires-Dist: brainunit; extra == "cuda12"
Requires-Dist: brainstate; extra == "cuda12"
Requires-Dist: brainpy; extra == "cuda12"
Requires-Dist: braintools; extra == "cuda12"
Provides-Extra: cuda13
Requires-Dist: jax[cuda13]; extra == "cuda13"
Requires-Dist: brainunit; extra == "cuda13"
Requires-Dist: brainstate; extra == "cuda13"
Requires-Dist: brainpy; extra == "cuda13"
Requires-Dist: braintools; extra == "cuda13"
Provides-Extra: tpu
Requires-Dist: jax[tpu]; extra == "tpu"
Requires-Dist: brainunit; extra == "tpu"
Requires-Dist: brainstate; extra == "tpu"
Requires-Dist: brainpy; extra == "tpu"
Requires-Dist: braintools; extra == "tpu"
Provides-Extra: testing
Requires-Dist: pytest; extra == "testing"
Requires-Dist: jax[cpu]; extra == "testing"
Requires-Dist: brainunit; extra == "testing"
Requires-Dist: brainstate; extra == "testing"
Requires-Dist: brainpy; extra == "testing"
Requires-Dist: braintools; extra == "testing"
Dynamic: license-file
